[
  {"api": "Aceh Barat", "display": "Aceh Barat (Kabupaten)", "province": "Aceh"},
  {"api": "Aceh Barat Daya", "display": "Aceh Barat Daya (Kabupaten)", "province": "Aceh"},
  {"api": "Aceh Besar", "display": "Aceh Besar (Kabupaten)", "province": "Aceh"},
  {"api": "Aceh Jaya", "display": "Aceh Jaya (Kabupaten)", "province": "Aceh"},
  {"api": "Aceh Selatan", "display": "Aceh Selatan (Kabupaten)", "province": "Aceh"},
  {"api": "Aceh Singkil", "display": "Aceh Singkil (Kabupaten)", "province": "Aceh"},
  {"api": "Aceh Tamiang", "display": "Aceh Tamiang (Kabupaten)", "province": "Aceh"},
  {"api": "Aceh Tengah", "display": "Aceh Tengah (Kabupaten)", "province": "Aceh"},
  {"api": "Aceh Tenggara", "display": "Aceh Tenggara (Kabupaten)", "province": "Aceh"},
  {"api": "Aceh Timur", "display": "Aceh Timur (Kabupaten)", "province": "Aceh"},
  {"api": "Aceh Utara", "display": "Aceh Utara (Kabupaten)", "province": "Aceh"},
  {"api": "Agam", "display": "Agam (Kabupaten)", "province": "Sumatera Barat"},
  {"api": "Alor", "display": "Alor (Kabupaten)", "province": "Nusa Tenggara Timur"},
  {"api": "Ambon", "display": "Ambon (Kota)", "province": "Maluku"},
  {"api": "Asahan", "display": "Asahan (Kabupaten)", "province": "Sumatera Utara"},
  {"api": "Asmat", "display": "Asmat (Kabupaten)", "province": "Papua Selatan"},
  
  {"api": "Badung", "display": "Badung (Kabupaten)", "province": "Bali"},
  {"api": "Balikpapan", "display": "Balikpapan (Kota)", "province": "Kalimantan Timur"},
  {"api": "Balangan", "display": "Balangan (Kabupaten)", "province": "Kalimantan Selatan"},
  {"api": "Banda Aceh", "display": "Banda Aceh (Kota)", "province": "Aceh"},
  {"api": "Bandar Lampung", "display": "Bandar Lampung (Kota)", "province": "Lampung"},
  {"api": "Bandung", "display": "Bandung (Kota)", "province": "Jawa Barat"},
  {"api": "Bandung", "display": "Bandung (Kabupaten)", "province": "Jawa Barat"},
  {"api": "Bandung Barat", "display": "Bandung Barat (Kabupaten)", "province": "Jawa Barat"},
  {"api": "Banggai", "display": "Banggai (Kabupaten)", "province": "Sulawesi Tengah"},
  {"api": "Banggai Kepulauan", "display": "Banggai Kepulauan (Kabupaten)", "province": "Sulawesi Tengah"},
  {"api": "Banggai Laut", "display": "Banggai Laut (Kabupaten)", "province": "Sulawesi Tengah"},
  {"api": "Bangka", "display": "Bangka (Kabupaten)", "province": "Kepulauan Bangka Belitung"},
  {"api": "Bangka Barat", "display": "Bangka Barat (Kabupaten)", "province": "Kepulauan Bangka Belitung"},
  {"api": "Bangka Selatan", "display": "Bangka Selatan (Kabupaten)", "province": "Kepulauan Bangka Belitung"},
  {"api": "Bangka Tengah", "display": "Bangka Tengah (Kabupaten)", "province": "Kepulauan Bangka Belitung"},
  {"api": "Bangkalan", "display": "Bangkalan (Kabupaten)", "province": "Jawa Timur"},
  {"api": "Bangli", "display": "Bangli (Kabupaten)", "province": "Bali"},
  {"api": "Banjar", "display": "Banjar (Kabupaten)", "province": "Kalimantan Selatan"},
  {"api": "Banjar", "display": "Banjar (Kota)", "province": "Jawa Barat"},
  {"api": "Banjarbaru", "display": "Banjarbaru (Kota)", "province": "Kalimantan Selatan"},
  {"api": "Banjarmasin", "display": "Banjarmasin (Kota)", "province": "Kalimantan Selatan"},
  {"api": "Banjarnegara", "display": "Banjarnegara (Kabupaten)", "province": "Jawa Tengah"},
  {"api": "Bantaeng", "display": "Bantaeng (Kabupaten)", "province": "Sulawesi Selatan"},
  {"api": "Bantul", "display": "Bantul (Kabupaten)", "province": "DI Yogyakarta"},
  {"api": "Banyuasin", "display": "Banyuasin (Kabupaten)", "province": "Sumatera Selatan"},
  {"api": "Banyumas", "display": "Banyumas (Kabupaten)", "province": "Jawa Tengah"},
  {"api": "Banyuwangi", "display": "Banyuwangi (Kabupaten)", "province": "Jawa Timur"},
  {"api": "Barito Kuala", "display": "Barito Kuala (Kabupaten)", "province": "Kalimantan Selatan"},
  {"api": "Barito Selatan", "display": "Barito Selatan (Kabupaten)", "province": "Kalimantan Tengah"},
  {"api": "Barito Timur", "display": "Barito Timur (Kabupaten)", "province": "Kalimantan Tengah"},
  {"api": "Barito Utara", "display": "Barito Utara (Kabupaten)", "province": "Kalimantan Tengah"},
  {"api": "Barru", "display": "Barru (Kabupaten)", "province": "Sulawesi Selatan"},
  {"api": "Batam", "display": "Batam (Kota)", "province": "Kepulauan Riau"},
  {"api": "Batang", "display": "Batang (Kabupaten)", "province": "Jawa Tengah"},
  {"api": "Batanghari", "display": "Batanghari (Kabupaten)", "province": "Jambi"},
  {"api": "Batu", "display": "Batu (Kota)", "province": "Jawa Timur"},
  {"api": "Batubara", "display": "Batubara (Kabupaten)", "province": "Sumatera Utara"},
  {"api": "Bau-Bau", "display": "Bau-Bau (Kota)", "province": "Sulawesi Tenggara"},
  {"api": "Bekasi", "display": "Bekasi (Kota)", "province": "Jawa Barat"},
  {"api": "Bekasi", "display": "Bekasi (Kabupaten)", "province": "Jawa Barat"},
  {"api": "Belitung", "display": "Belitung (Kabupaten)", "province": "Kepulauan Bangka Belitung"},
  {"api": "Belitung Timur", "display": "Belitung Timur (Kabupaten)", "province": "Kepulauan Bangka Belitung"},
  {"api": "Belu", "display": "Belu (Kabupaten)", "province": "Nusa Tenggara Timur"},
  {"api": "Bener Meriah", "display": "Bener Meriah (Kabupaten)", "province": "Aceh"},
  {"api": "Bengkalis", "display": "Bengkalis (Kabupaten)", "province": "Riau"},
  {"api": "Bengkayang", "display": "Bengkayang (Kabupaten)", "province": "Kalimantan Barat"},
  {"api": "Bengkulu", "display": "Bengkulu (Kota)", "province": "Bengkulu"},
  {"api": "Bengkulu Selatan", "display": "Bengkulu Selatan (Kabupaten)", "province": "Bengkulu"},
  {"api": "Bengkulu Tengah", "display": "Bengkulu Tengah (Kabupaten)", "province": "Bengkulu"},
  {"api": "Bengkulu Utara", "display": "Bengkulu Utara (Kabupaten)", "province": "Bengkulu"},
  {"api": "Berau", "display": "Berau (Kabupaten)", "province": "Kalimantan Timur"},
  {"api": "Biak Numfor", "display": "Biak Numfor (Kabupaten)", "province": "Papua"},
  {"api": "Bima", "display": "Bima (Kota)", "province": "Nusa Tenggara Barat"},
  {"api": "Bima", "display": "Bima (Kabupaten)", "province": "Nusa Tenggara Barat"},
  {"api": "Binjai", "display": "Binjai (Kota)", "province": "Sumatera Utara"},
  {"api": "Bintan", "display": "Bintan (Kabupaten)", "province": "Kepulauan Riau"},
  {"api": "Bireuen", "display": "Bireuen (Kabupaten)", "province": "Aceh"},
  {"api": "Bitung", "display": "Bitung (Kota)", "province": "Sulawesi Utara"},
  {"api": "Blitar", "display": "Blitar (Kota)", "province": "Jawa Timur"},
  {"api": "Blitar", "display": "Blitar (Kabupaten)", "province": "Jawa Timur"},
  {"api": "Blora", "display": "Blora (Kabupaten)", "province": "Jawa Tengah"},
  {"api": "Boalemo", "display": "Boalemo (Kabupaten)", "province": "Gorontalo"},
  {"api": "Bogor", "display": "Bogor (Kota)", "province": "Jawa Barat"},
  {"api": "Bogor", "display": "Bogor (Kabupaten)", "province": "Jawa Barat"},
  {"api": "Bojonegoro", "display": "Bojonegoro (Kabupaten)", "province": "Jawa Timur"},
  {"api": "Bolaang Mongondow", "display": "Bolaang Mongondow (Kabupaten)", "province": "Sulawesi Utara"},
  {"api": "Bolaang Mongondow Selatan", "display": "Bolaang Mongondow Selatan (Kabupaten)", "province": "Sulawesi Utara"},
  {"api": "Bolaang Mongondow Timur", "display": "Bolaang Mongondow Timur (Kabupaten)", "province": "Sulawesi Utara"},
  {"api": "Bolaang Mongondow Utara", "display": "Bolaang Mongondow Utara (Kabupaten)", "province": "Sulawesi Utara"},
  {"api": "Bombana", "display": "Bombana (Kabupaten)", "province": "Sulawesi Tenggara"},
  {"api": "Bondowoso", "display": "Bondowoso (Kabupaten)", "province": "Jawa Timur"},
  {"api": "Bone", "display": "Bone (Kabupaten)", "province": "Sulawesi Selatan"},
  {"api": "Bone Bolango", "display": "Bone Bolango (Kabupaten)", "province": "Gorontalo"},
  {"api": "Bontang", "display": "Bontang (Kota)", "province": "Kalimantan Timur"},
  {"api": "Boven Digoel", "display": "Boven Digoel (Kabupaten)", "province": "Papua Selatan"},
  {"api": "Boyolali", "display": "Boyolali (Kabupaten)", "province": "Jawa Tengah"},
  {"api": "Brebes", "display": "Brebes (Kabupaten)", "province": "Jawa Tengah"},
  {"api": "Bukittinggi", "display": "Bukittinggi (Kota)", "province": "Sumatera Barat"},
  {"api": "Buleleng", "display": "Buleleng (Kabupaten)", "province": "Bali"},
  {"api": "Bulukumba", "display": "Bulukumba (Kabupaten)", "province": "Sulawesi Selatan"},
  {"api": "Bulungan", "display": "Bulungan (Kabupaten)", "province": "Kalimantan Utara"},
  {"api": "Bungo", "display": "Bungo (Kabupaten)", "province": "Jambi"},
  {"api": "Buol", "display": "Buol (Kabupaten)", "province": "Sulawesi Tengah"},
  {"api": "Buru", "display": "Buru (Kabupaten)", "province": "Maluku"},
  {"api": "Buru Selatan", "display": "Buru Selatan (Kabupaten)", "province": "Maluku"},
  {"api": "Buton", "display": "Buton (Kabupaten)", "province": "Sulawesi Tenggara"},
  {"api": "Buton Selatan", "display": "Buton Selatan (Kabupaten)", "province": "Sulawesi Tenggara"},
  {"api": "Buton Tengah", "display": "Buton Tengah (Kabupaten)", "province": "Sulawesi Tenggara"},
  {"api": "Buton Utara", "display": "Buton Utara (Kabupaten)", "province": "Sulawesi Tenggara"},
  
  {"api": "Ciamis", "display": "Ciamis (Kabupaten)", "province": "Jawa Barat"},
  {"api": "Cianjur", "display": "Cianjur (Kabupaten)", "province": "Jawa Barat"},
  {"api": "Cilacap", "display": "Cilacap (Kabupaten)", "province": "Jawa Tengah"},
  {"api": "Cilegon", "display": "Cilegon (Kota)", "province": "Banten"},
  {"api": "Cimahi", "display": "Cimahi (Kota)", "province": "Jawa Barat"},
  {"api": "Cirebon", "display": "Cirebon (Kota)", "province": "Jawa Barat"},
  {"api": "Cirebon", "display": "Cirebon (Kabupaten)", "province": "Jawa Barat"},
  
  {"api": "Dairi", "display": "Dairi (Kabupaten)", "province": "Sumatera Utara"},
  {"api": "Deiyai", "display": "Deiyai (Kabupaten)", "province": "Papua Tengah"},
  {"api": "Deli Serdang", "display": "Deli Serdang (Kabupaten)", "province": "Sumatera Utara"},
  {"api": "Demak", "display": "Demak (Kabupaten)", "province": "Jawa Tengah"},
  {"api": "Denpasar", "display": "Denpasar (Kota)", "province": "Bali"},
  {"api": "Depok", "display": "Depok (Kota)", "province": "Jawa Barat"},
  {"api": "Dharmasraya", "display": "Dharmasraya (Kabupaten)", "province": "Sumatera Barat"},
  {"api": "Dogiyai", "display": "Dogiyai (Kabupaten)", "province": "Papua Tengah"},
  {"api": "Dompu", "display": "Dompu (Kabupaten)", "province": "Nusa Tenggara Barat"},
  {"api": "Donggala", "display": "Donggala (Kabupaten)", "province": "Sulawesi Tengah"},
  {"api": "Dumai", "display": "Dumai (Kota)", "province": "Riau"},
  
  {"api": "Empat Lawang", "display": "Empat Lawang (Kabupaten)", "province": "Sumatera Selatan"},
  {"api": "Ende", "display": "Ende (Kabupaten)", "province": "Nusa Tenggara Timur"},
  {"api": "Enrekang", "display": "Enrekang (Kabupaten)", "province": "Sulawesi Selatan"},
  
  {"api": "Fakfak", "display": "Fakfak (Kabupaten)", "province": "Papua Barat Daya"},
  {"api": "Flores Timur", "display": "Flores Timur (Kabupaten)", "province": "Nusa Tenggara Timur"},
  
  {"api": "Garut", "display": "Garut (Kabupaten)", "province": "Jawa Barat"},
  {"api": "Gayo Lues", "display": "Gayo Lues (Kabupaten)", "province": "Aceh"},
  {"api": "Gianyar", "display": "Gianyar (Kabupaten)", "province": "Bali"},
  {"api": "Gorontalo", "display": "Gorontalo (Kota)", "province": "Gorontalo"},
  {"api": "Gorontalo", "display": "Gorontalo (Kabupaten)", "province": "Gorontalo"},
  {"api": "Gorontalo Utara", "display": "Gorontalo Utara (Kabupaten)", "province": "Gorontalo"},
  {"api": "Gowa", "display": "Gowa (Kabupaten)", "province": "Sulawesi Selatan"},
  {"api": "Gresik", "display": "Gresik (Kabupaten)", "province": "Jawa Timur"},
  {"api": "Grobogan", "display": "Grobogan (Kabupaten)", "province": "Jawa Tengah"},
  {"api": "Gunung Mas", "display": "Gunung Mas (Kabupaten)", "province": "Kalimantan Tengah"},
  {"api": "Gunungkidul", "display": "Gunungkidul (Kabupaten)", "province": "DI Yogyakarta"},
  {"api": "Gunungsitoli", "display": "Gunungsitoli (Kota)", "province": "Sumatera Utara"},
  
  {"api": "Halmahera Barat", "display": "Halmahera Barat (Kabupaten)", "province": "Maluku Utara"},
  {"api": "Halmahera Selatan", "display": "Halmahera Selatan (Kabupaten)", "province": "Maluku Utara"},
  {"api": "Halmahera Tengah", "display": "Halmahera Tengah (Kabupaten)", "province": "Maluku Utara"},
  {"api": "Halmahera Timur", "display": "Halmahera Timur (Kabupaten)", "province": "Maluku Utara"},
  {"api": "Halmahera Utara", "display": "Halmahera Utara (Kabupaten)", "province": "Maluku Utara"},
  {"api": "Hulu Sungai Selatan", "display": "Hulu Sungai Selatan (Kabupaten)", "province": "Kalimantan Selatan"},
  {"api": "Hulu Sungai Tengah", "display": "Hulu Sungai Tengah (Kabupaten)", "province": "Kalimantan Selatan"},
  {"api": "Hulu Sungai Utara", "display": "Hulu Sungai Utara (Kabupaten)", "province": "Kalimantan Selatan"},
  {"api": "Humbang Hasundutan", "display": "Humbang Hasundutan (Kabupaten)", "province": "Sumatera Utara"},
  
  {"api": "Indragiri Hilir", "display": "Indragiri Hilir (Kabupaten)", "province": "Riau"},
  {"api": "Indragiri Hulu", "display": "Indragiri Hulu (Kabupaten)", "province": "Riau"},
  {"api": "Indramayu", "display": "Indramayu (Kabupaten)", "province": "Jawa Barat"},
  {"api": "Intan Jaya", "display": "Intan Jaya (Kabupaten)", "province": "Papua Tengah"},
  
  {"api": "Jakarta Barat", "display": "Jakarta Barat (Kota Administrasi)", "province": "DKI Jakarta"},
  {"api": "Jakarta Pusat", "display": "Jakarta Pusat (Kota Administrasi)", "province": "DKI Jakarta"},
  {"api": "Jakarta Selatan", "display": "Jakarta Selatan (Kota Administrasi)", "province": "DKI Jakarta"},
  {"api": "Jakarta Timur", "display": "Jakarta Timur (Kota Administrasi)", "province": "DKI Jakarta"},
  {"api": "Jakarta Utara", "display": "Jakarta Utara (Kota Administrasi)", "province": "DKI Jakarta"},
  {"api": "Jambi", "display": "Jambi (Kota)", "province": "Jambi"},
  {"api": "Jayapura", "display": "Jayapura (Kota)", "province": "Papua"},
  {"api": "Jayapura", "display": "Jayapura (Kabupaten)", "province": "Papua"},
  {"api": "Jayawijaya", "display": "Jayawijaya (Kabupaten)", "province": "Papua Pegunungan"},
  {"api": "Jember", "display": "Jember (Kabupaten)", "province": "Jawa Timur"},
  {"api": "Jembrana", "display": "Jembrana (Kabupaten)", "province": "Bali"},
  {"api": "Jeneponto", "display": "Jeneponto (Kabupaten)", "province": "Sulawesi Selatan"},
  {"api": "Jepara", "display": "Jepara (Kabupaten)", "province": "Jawa Tengah"},
  {"api": "Jombang", "display": "Jombang (Kabupaten)", "province": "Jawa Timur"},
  
  {"api": "Kaimana", "display": "Kaimana (Kabupaten)", "province": "Papua Barat Daya"},
  {"api": "Kampar", "display": "Kampar (Kabupaten)", "province": "Riau"},
  {"api": "Kapuas", "display": "Kapuas (Kabupaten)", "province": "Kalimantan Tengah"},
  {"api": "Kapuas Hulu", "display": "Kapuas Hulu (Kabupaten)", "province": "Kalimantan Barat"},
  {"api": "Karanganyar", "display": "Karanganyar (Kabupaten)", "province": "Jawa Tengah"},
  {"api": "Karangasem", "display": "Karangasem (Kabupaten)", "province": "Bali"},
  {"api": "Karawang", "display": "Karawang (Kabupaten)", "province": "Jawa Barat"},
  {"api": "Karimun", "display": "Karimun (Kabupaten)", "province": "Kepulauan Riau"},
  {"api": "Karo", "display": "Karo (Kabupaten)", "province": "Sumatera Utara"},
  {"api": "Katingan", "display": "Katingan (Kabupaten)", "province": "Kalimantan Tengah"},
  {"api": "Kaur", "display": "Kaur (Kabupaten)", "province": "Bengkulu"},
  {"api": "Kayong Utara", "display": "Kayong Utara (Kabupaten)", "province": "Kalimantan Barat"},
  {"api": "Kebumen", "display": "Kebumen (Kabupaten)", "province": "Jawa Tengah"},
  {"api": "Kediri", "display": "Kediri (Kota)", "province": "Jawa Timur"},
  {"api": "Kediri", "display": "Kediri (Kabupaten)", "province": "Jawa Timur"},
  {"api": "Keerom", "display": "Keerom (Kabupaten)", "province": "Papua"},
  {"api": "Kendal", "display": "Kendal (Kabupaten)", "province": "Jawa Tengah"},
  {"api": "Kendari", "display": "Kendari (Kota)", "province": "Sulawesi Tenggara"},
  {"api": "Kepahiang", "display": "Kepahiang (Kabupaten)", "province": "Bengkulu"},
  {"api": "Kepulauan Anambas", "display": "Kepulauan Anambas (Kabupaten)", "province": "Kepulauan Riau"},
  {"api": "Kepulauan Aru", "display": "Kepulauan Aru (Kabupaten)", "province": "Maluku"},
  {"api": "Kepulauan Meranti", "display": "Kepulauan Meranti (Kabupaten)", "province": "Riau"},
  {"api": "Kepulauan Mentawai", "display": "Kepulauan Mentawai (Kabupaten)", "province": "Sumatera Barat"},
  {"api": "Kepulauan Sangihe", "display": "Kepulauan Sangihe (Kabupaten)", "province": "Sulawesi Utara"},
  {"api": "Kepulauan Selayar", "display": "Kepulauan Selayar (Kabupaten)", "province": "Sulawesi Selatan"},
  {"api": "Kepulauan Seribu", "display": "Kepulauan Seribu (Kabupaten Administrasi)", "province": "DKI Jakarta"},
  {"api": "Kepulauan Siau Tagulandang Biaro", "display": "Kepulauan Siau Tagulandang Biaro (Kabupaten)", "province": "Sulawesi Utara"},
  {"api": "Kepulauan Sula", "display": "Kepulauan Sula (Kabupaten)", "province": "Maluku Utara"},
  {"api": "Kepulauan Talaud", "display": "Kepulauan Talaud (Kabupaten)", "province": "Sulawesi Utara"},
  {"api": "Kepulauan Yapen", "display": "Kepulauan Yapen (Kabupaten)", "province": "Papua"},
  {"api": "Kerinci", "display": "Kerinci (Kabupaten)", "province": "Jambi"},
  {"api": "Ketapang", "display": "Ketapang (Kabupaten)", "province": "Kalimantan Barat"},
  {"api": "Klaten", "display": "Klaten (Kabupaten)", "province": "Jawa Tengah"},
  {"api": "Klungkung", "display": "Klungkung (Kabupaten)", "province": "Bali"},
  {"api": "Kolaka", "display": "Kolaka (Kabupaten)", "province": "Sulawesi Tenggara"},
  {"api": "Kolaka Timur", "display": "Kolaka Timur (Kabupaten)", "province": "Sulawesi Tenggara"},
  {"api": "Kolaka Utara", "display": "Kolaka Utara (Kabupaten)", "province": "Sulawesi Tenggara"},
  {"api": "Konawe", "display": "Konawe (Kabupaten)", "province": "Sulawesi Tenggara"},
  {"api": "Konawe Kepulauan", "display": "Konawe Kepulauan (Kabupaten)", "province": "Sulawesi Tenggara"},
  {"api": "Konawe Selatan", "display": "Konawe Selatan (Kabupaten)", "province": "Sulawesi Tenggara"},
  {"api": "Konawe Utara", "display": "Konawe Utara (Kabupaten)", "province": "Sulawesi Tenggara"},
  {"api": "Kotabaru", "display": "Kotabaru (Kabupaten)", "province": "Kalimantan Selatan"},
  {"api": "Kotamobagu", "display": "Kotamobagu (Kota)", "province": "Sulawesi Utara"},
  {"api": "Kotawaringin Barat", "display": "Kotawaringin Barat (Kabupaten)", "province": "Kalimantan Tengah"},
  {"api": "Kotawaringin Timur", "display": "Kotawaringin Timur (Kabupaten)", "province": "Kalimantan Tengah"},
  {"api": "Kuantan Singingi", "display": "Kuantan Singingi (Kabupaten)", "province": "Riau"},
  {"api": "Kubu Raya", "display": "Kubu Raya (Kabupaten)", "province": "Kalimantan Barat"},
  {"api": "Kudus", "display": "Kudus (Kabupaten)", "province": "Jawa Tengah"},
  {"api": "Kulon Progo", "display": "Kulon Progo (Kabupaten)", "province": "DI Yogyakarta"},
  {"api": "Kuningan", "display": "Kuningan (Kabupaten)", "province": "Jawa Barat"},
  {"api": "Kupang", "display": "Kupang (Kota)", "province": "Nusa Tenggara Timur"},
  {"api": "Kupang", "display": "Kupang (Kabupaten)", "province": "Nusa Tenggara Timur"},
  {"api": "Kutai Barat", "display": "Kutai Barat (Kabupaten)", "province": "Kalimantan Timur"},
  {"api": "Kutai Kartanegara", "display": "Kutai Kartanegara (Kabupaten)", "province": "Kalimantan Timur"},
  {"api": "Kutai Timur", "display": "Kutai Timur (Kabupaten)", "province": "Kalimantan Timur"},
  
  {"api": "Labuhanbatu", "display": "Labuhanbatu (Kabupaten)", "province": "Sumatera Utara"},
  {"api": "Labuhanbatu Selatan", "display": "Labuhanbatu Selatan (Kabupaten)", "province": "Sumatera Utara"},
  {"api": "Labuhanbatu Utara", "display": "Labuhanbatu Utara (Kabupaten)", "province": "Sumatera Utara"},
  {"api": "Lahat", "display": "Lahat (Kabupaten)", "province": "Sumatera Selatan"},
  {"api": "Lamandau", "display": "Lamandau (Kabupaten)", "province": "Kalimantan Tengah"},
  {"api": "Lamongan", "display": "Lamongan (Kabupaten)", "province": "Jawa Timur"},
  {"api": "Lampung Barat", "display": "Lampung Barat (Kabupaten)", "province": "Lampung"},
  {"api": "Lampung Selatan", "display": "Lampung Selatan (Kabupaten)", "province": "Lampung"},
  {"api": "Lampung Tengah", "display": "Lampung Tengah (Kabupaten)", "province": "Lampung"},
  {"api": "Lampung Timur", "display": "Lampung Timur (Kabupaten)", "province": "Lampung"},
  {"api": "Lampung Utara", "display": "Lampung Utara (Kabupaten)", "province": "Lampung"},
  {"api": "Landak", "display": "Landak (Kabupaten)", "province": "Kalimantan Barat"},
  {"api": "Langkat", "display": "Langkat (Kabupaten)", "province": "Sumatera Utara"},
  {"api": "Langsa", "display": "Langsa (Kota)", "province": "Aceh"},
  {"api": "Lanny Jaya", "display": "Lanny Jaya (Kabupaten)", "province": "Papua Pegunungan"},
  {"api": "Lebak", "display": "Lebak (Kabupaten)", "province": "Banten"},
  {"api": "Lebong", "display": "Lebong (Kabupaten)", "province": "Bengkulu"},
  {"api": "Lembata", "display": "Lembata (Kabupaten)", "province": "Nusa Tenggara Timur"},
  {"api": "Lhokseumawe", "display": "Lhokseumawe (Kota)", "province": "Aceh"},
  {"api": "Lima Puluh Kota", "display": "Lima Puluh Kota (Kabupaten)", "province": "Sumatera Barat"},
  {"api": "Lingga", "display": "Lingga (Kabupaten)", "province": "Kepulauan Riau"},
  {"api": "Lombok Barat", "display": "Lombok Barat (Kabupaten)", "province": "Nusa Tenggara Barat"},
  {"api": "Lombok Tengah", "display": "Lombok Tengah (Kabupaten)", "province": "Nusa Tenggara Barat"},
  {"api": "Lombok Timur", "display": "Lombok Timur (Kabupaten)", "province": "Nusa Tenggara Barat"},
  {"api": "Lombok Utara", "display": "Lombok Utara (Kabupaten)", "province": "Nusa Tenggara Barat"},
  {"api": "Lubuklinggau", "display": "Lubuklinggau (Kota)", "province": "Sumatera Selatan"},
  {"api": "Lumajang", "display": "Lumajang (Kabupaten)", "province": "Jawa Timur"},
  {"api": "Luwu", "display": "Luwu (Kabupaten)", "province": "Sulawesi Selatan"},
  {"api": "Luwu Timur", "display": "Luwu Timur (Kabupaten)", "province": "Sulawesi Selatan"},
  {"api": "Luwu Utara", "display": "Luwu Utara (Kabupaten)", "province": "Sulawesi Selatan"},
  
  {"api": "Madiun", "display": "Madiun (Kota)", "province": "Jawa Timur"},
  {"api": "Madiun", "display": "Madiun (Kabupaten)", "province": "Jawa Timur"},
  {"api": "Magelang", "display": "Magelang (Kota)", "province": "Jawa Tengah"},
  {"api": "Magelang", "display": "Magelang (Kabupaten)", "province": "Jawa Tengah"},
  {"api": "Magetan", "display": "Magetan (Kabupaten)", "province": "Jawa Timur"},
  {"api": "Mahakam Ulu", "display": "Mahakam Ulu (Kabupaten)", "province": "Kalimantan Timur"},
  {"api": "Majalengka", "display": "Majalengka (Kabupaten)", "province": "Jawa Barat"},
  {"api": "Majene", "display": "Majene (Kabupaten)", "province": "Sulawesi Barat"},
  {"api": "Makassar", "display": "Makassar (Kota)", "province": "Sulawesi Selatan"},
  {"api": "Malaka", "display": "Malaka (Kabupaten)", "province": "Nusa Tenggara Timur"},
  {"api": "Malang", "display": "Malang (Kota)", "province": "Jawa Timur"},
  {"api": "Malang", "display": "Malang (Kabupaten)", "province": "Jawa Timur"},
  {"api": "Malinau", "display": "Malinau (Kabupaten)", "province": "Kalimantan Utara"},
  {"api": "Maluku Barat Daya", "display": "Maluku Barat Daya (Kabupaten)", "province": "Maluku"},
  {"api": "Maluku Tengah", "display": "Maluku Tengah (Kabupaten)", "province": "Maluku"},
  {"api": "Maluku Tenggara", "display": "Maluku Tenggara (Kabupaten)", "province": "Maluku"},
  {"api": "Maluku Tenggara Barat", "display": "Maluku Tenggara Barat (Kabupaten)", "province": "Maluku"},
  {"api": "Mamasa", "display": "Mamasa (Kabupaten)", "province": "Sulawesi Barat"},
  {"api": "Mamberamo Raya", "display": "Mamberamo Raya (Kabupaten)", "province": "Papua"},
  {"api": "Mamberamo Tengah", "display": "Mamberamo Tengah (Kabupaten)", "province": "Papua Pegunungan"},
  {"api": "Mamuju", "display": "Mamuju (Kabupaten)", "province": "Sulawesi Barat"},
  {"api": "Mamuju Tengah", "display": "Mamuju Tengah (Kabupaten)", "province": "Sulawesi Barat"},
  {"api": "Mamuju Utara", "display": "Mamuju Utara (Kabupaten)", "province": "Sulawesi Barat"},
  {"api": "Manado", "display": "Manado (Kota)", "province": "Sulawesi Utara"},
  {"api": "Mandailing Natal", "display": "Mandailing Natal (Kabupaten)", "province": "Sumatera Utara"},
  {"api": "Manggarai", "display": "Manggarai (Kabupaten)", "province": "Nusa Tenggara Timur"},
  {"api": "Manggarai Barat", "display": "Manggarai Barat (Kabupaten)", "province": "Nusa Tenggara Timur"},
  {"api": "Manggarai Timur", "display": "Manggarai Timur (Kabupaten)", "province": "Nusa Tenggara Timur"},
  {"api": "Manokwari", "display": "Manokwari (Kabupaten)", "province": "Papua Barat"},
  {"api": "Manokwari Selatan", "display": "Manokwari Selatan (Kabupaten)", "province": "Papua Barat"},
  {"api": "Mappi", "display": "Mappi (Kabupaten)", "province": "Papua Selatan"},
  {"api": "Maros", "display": "Maros (Kabupaten)", "province": "Sulawesi Selatan"},
  {"api": "Mataram", "display": "Mataram (Kota)", "province": "Nusa Tenggara Barat"},
  {"api": "Maybrat", "display": "Maybrat (Kabupaten)", "province": "Papua Barat Daya"},
  {"api": "Medan", "display": "Medan (Kota)", "province": "Sumatera Utara"},
  {"api": "Melawi", "display": "Melawi (Kabupaten)", "province": "Kalimantan Barat"},
  {"api": "Mempawah", "display": "Mempawah (Kota)", "province": "Kalimantan Barat"},
  {"api": "Merangin", "display": "Merangin (Kabupaten)", "province": "Jambi"},
  {"api": "Merauke", "display": "Merauke (Kabupaten)", "province": "Papua Selatan"},
  {"api": "Mesuji", "display": "Mesuji (Kabupaten)", "province": "Lampung"},
  {"api": "Metro", "display": "Metro (Kota)", "province": "Lampung"},
  {"api": "Mimika", "display": "Mimika (Kabupaten)", "province": "Papua Tengah"},
  {"api": "Minahasa", "display": "Minahasa (Kabupaten)", "province": "Sulawesi Utara"},
  {"api": "Minahasa Selatan", "display": "Minahasa Selatan (Kabupaten)", "province": "Sulawesi Utara"},
  {"api": "Minahasa Tenggara", "display": "Minahasa Tenggara (Kabupaten)", "province": "Sulawesi Utara"},
  {"api": "Minahasa Utara", "display": "Minahasa Utara (Kabupaten)", "province": "Sulawesi Utara"},
  {"api": "Mojokerto", "display": "Mojokerto (Kota)", "province": "Jawa Timur"},
  {"api": "Mojokerto", "display": "Mojokerto (Kabupaten)", "province": "Jawa Timur"},
  {"api": "Morowali", "display": "Morowali (Kabupaten)", "province": "Sulawesi Tengah"},
  {"api": "Morowali Utara", "display": "Morowali Utara (Kabupaten)", "province": "Sulawesi Tengah"},
  {"api": "Muara Enim", "display": "Muara Enim (Kabupaten)", "province": "Sumatera Selatan"},
  {"api": "Muaro Jambi", "display": "Muaro Jambi (Kabupaten)", "province": "Jambi"},
  {"api": "Mukomuko", "display": "Mukomuko (Kabupaten)", "province": "Bengkulu"},
  {"api": "Muna", "display": "Muna (Kabupaten)", "province": "Sulawesi Tenggara"},
  {"api": "Muna Barat", "display": "Muna Barat (Kabupaten)", "province": "Sulawesi Tenggara"},
  {"api": "Murung Raya", "display": "Murung Raya (Kabupaten)", "province": "Kalimantan Tengah"},
  {"api": "Musi Banyuasin", "display": "Musi Banyuasin (Kabupaten)", "province": "Sumatera Selatan"},
  {"api": "Musi Rawas", "display": "Musi Rawas (Kabupaten)", "province": "Sumatera Selatan"},
  {"api": "Musi Rawas Utara", "display": "Musi Rawas Utara (Kabupaten)", "province": "Sumatera Selatan"},
  
  {"api": "Nabire", "display": "Nabire (Kabupaten)", "province": "Papua Tengah"},
  {"api": "Nagan Raya", "display": "Nagan Raya (Kabupaten)", "province": "Aceh"},
  {"api": "Nagekeo", "display": "Nagekeo (Kabupaten)", "province": "Nusa Tenggara Timur"},
  {"api": "Natuna", "display": "Natuna (Kabupaten)", "province": "Kepulauan Riau"},
  {"api": "Nduga", "display": "Nduga (Kabupaten)", "province": "Papua Pegunungan"},
  {"api": "Ngada", "display": "Ngada (Kabupaten)", "province": "Nusa Tenggara Timur"},
  {"api": "Nganjuk", "display": "Nganjuk (Kabupaten)", "province": "Jawa Timur"},
  {"api": "Ngawi", "display": "Ngawi (Kabupaten)", "province": "Jawa Timur"},
  {"api": "Nias", "display": "Nias (Kabupaten)", "province": "Sumatera Utara"},
  {"api": "Nias Barat", "display": "Nias Barat (Kabupaten)", "province": "Sumatera Utara"},
  {"api": "Nias Selatan", "display": "Nias Selatan (Kabupaten)", "province": "Sumatera Utara"},
  {"api": "Nias Utara", "display": "Nias Utara (Kabupaten)", "province": "Sumatera Utara"},
  {"api": "Nunukan", "display": "Nunukan (Kabupaten)", "province": "Kalimantan Utara"},
  
  {"api": "Ogan Ilir", "display": "Ogan Ilir (Kabupaten)", "province": "Sumatera Selatan"},
  {"api": "Ogan Komering Ilir", "display": "Ogan Komering Ilir (Kabupaten)", "province": "Sumatera Selatan"},
  {"api": "Ogan Komering Ulu", "display": "Ogan Komering Ulu (Kabupaten)", "province": "Sumatera Selatan"},
  {"api": "Ogan Komering Ulu Selatan", "display": "Ogan Komering Ulu Selatan (Kabupaten)", "province": "Sumatera Selatan"},
  {"api": "Ogan Komering Ulu Timur", "display": "Ogan Komering Ulu Timur (Kabupaten)", "province": "Sumatera Selatan"},
  
  {"api": "Pacitan", "display": "Pacitan (Kabupaten)", "province": "Jawa Timur"},
  {"api": "Padang", "display": "Padang (Kota)", "province": "Sumatera Barat"},
  {"api": "Padang Lawas", "display": "Padang Lawas (Kabupaten)", "province": "Sumatera Utara"},
  {"api": "Padang Lawas Utara", "display": "Padang Lawas Utara (Kabupaten)", "province": "Sumatera Utara"},
  {"api": "Padang Panjang", "display": "Padang Panjang (Kota)", "province": "Sumatera Barat"},
  {"api": "Padang Pariaman", "display": "Padang Pariaman (Kabupaten)", "province": "Sumatera Barat"},
  {"api": "Padang Sidempuan", "display": "Padang Sidempuan (Kota)", "province": "Sumatera Utara"},
  {"api": "Pagar Alam", "display": "Pagar Alam (Kota)", "province": "Sumatera Selatan"},
  {"api": "Pakpak Bharat", "display": "Pakpak Bharat (Kabupaten)", "province": "Sumatera Utara"},
  {"api": "Palangka Raya", "display": "Palangka Raya (Kota)", "province": "Kalimantan Tengah"},
  {"api": "Palembang", "display": "Palembang (Kota)", "province": "Sumatera Selatan"},
  {"api": "Palopo", "display": "Palopo (Kota)", "province": "Sulawesi Selatan"},
  {"api": "Palu", "display": "Palu (Kota)", "province": "Sulawesi Tengah"},
  {"api": "Pamekasan", "display": "Pamekasan (Kabupaten)", "province": "Jawa Timur"},
  {"api": "Pandeglang", "display": "Pandeglang (Kabupaten)", "province": "Banten"},
  {"api": "Pangandaran", "display": "Pangandaran (Kabupaten)", "province": "Jawa Barat"},
  {"api": "Pangkajene dan Kepulauan", "display": "Pangkajene dan Kepulauan (Kabupaten)", "province": "Sulawesi Selatan"},
  {"api": "Pangkal Pinang", "display": "Pangkal Pinang (Kota)", "province": "Kepulauan Bangka Belitung"},
  {"api": "Paniai", "display": "Paniai (Kabupaten)", "province": "Papua Tengah"},
  {"api": "Parepare", "display": "Parepare (Kota)", "province": "Sulawesi Selatan"},
  {"api": "Pariaman", "display": "Pariaman (Kota)", "province": "Sumatera Barat"},
  {"api": "Parigi Moutong", "display": "Parigi Moutong (Kabupaten)", "province": "Sulawesi Tengah"},
  {"api": "Pasaman", "display": "Pasaman (Kabupaten)", "province": "Sumatera Barat"},
  {"api": "Pasaman Barat", "display": "Pasaman Barat (Kabupaten)", "province": "Sumatera Barat"},
  {"api": "Paser", "display": "Paser (Kabupaten)", "province": "Kalimantan Timur"},
  {"api": "Pasuruan", "display": "Pasuruan (Kota)", "province": "Jawa Timur"},
  {"api": "Pasuruan", "display": "Pasuruan (Kabupaten)", "province": "Jawa Timur"},
  {"api": "Pati", "display": "Pati (Kabupaten)", "province": "Jawa Tengah"},
  {"api": "Payakumbuh", "display": "Payakumbuh (Kota)", "province": "Sumatera Barat"},
  {"api": "Pegunungan Arfak", "display": "Pegunungan Arfak (Kabupaten)", "province": "Papua Barat"},
  {"api": "Pegunungan Bintang", "display": "Pegunungan Bintang (Kabupaten)", "province": "Papua Pegunungan"},
  {"api": "Pekalongan", "display": "Pekalongan (Kota)", "province": "Jawa Tengah"},
  {"api": "Pekalongan", "display": "Pekalongan (Kabupaten)", "province": "Jawa Tengah"},
  {"api": "Pekanbaru", "display": "Pekanbaru (Kota)", "province": "Riau"},
  {"api": "Pelalawan", "display": "Pelalawan (Kabupaten)", "province": "Riau"},
  {"api": "Pemalang", "display": "Pemalang (Kabupaten)", "province": "Jawa Tengah"},
  {"api": "Pematang Siantar", "display": "Pematang Siantar (Kota)", "province": "Sumatera Utara"},
  {"api": "Penajam Paser Utara", "display": "Penajam Paser Utara (Kabupaten)", "province": "Kalimantan Timur"},
  {"api": "Penukal Abab Lematang Ilir", "display": "Penukal Abab Lematang Ilir (Kabupaten)", "province": "Sumatera Selatan"},
  {"api": "Pesawaran", "display": "Pesawaran (Kabupaten)", "province": "Lampung"},
  {"api": "Pesisir Barat", "display": "Pesisir Barat (Kabupaten)", "province": "Lampung"},
  {"api": "Pesisir Selatan", "display": "Pesisir Selatan (Kabupaten)", "province": "Sumatera Barat"},
  {"api": "Pidie", "display": "Pidie (Kabupaten)", "province": "Aceh"},
  {"api": "Pidie Jaya", "display": "Pidie Jaya (Kabupaten)", "province": "Aceh"},
  {"api": "Pinrang", "display": "Pinrang (Kabupaten)", "province": "Sulawesi Selatan"},
  {"api": "Pohuwato", "display": "Pohuwato (Kabupaten)", "province": "Gorontalo"},
  {"api": "Polewali Mandar", "display": "Polewali Mandar (Kabupaten)", "province": "Sulawesi Barat"},
  {"api": "Ponorogo", "display": "Ponorogo (Kabupaten)", "province": "Jawa Timur"},
  {"api": "Pontianak", "display": "Pontianak (Kota)", "province": "Kalimantan Barat"},
  {"api": "Poso", "display": "Poso (Kabupaten)", "province": "Sulawesi Tengah"},
  {"api": "Prabumulih", "display": "Prabumulih (Kota)", "province": "Sumatera Selatan"},
  {"api": "Pringsewu", "display": "Pringsewu (Kabupaten)", "province": "Lampung"},
  {"api": "Probolinggo", "display": "Probolinggo (Kota)", "province": "Jawa Timur"},
  {"api": "Probolinggo", "display": "Probolinggo (Kabupaten)", "province": "Jawa Timur"},
  {"api": "Pulang Pisau", "display": "Pulang Pisau (Kabupaten)", "province": "Kalimantan Tengah"},
  {"api": "Pulau Morotai", "display": "Pulau Morotai (Kabupaten)", "province": "Maluku Utara"},
  {"api": "Pulau Taliabu", "display": "Pulau Taliabu (Kabupaten)", "province": "Maluku Utara"},
  {"api": "Puncak", "display": "Puncak (Kabupaten)", "province": "Papua Tengah"},
  {"api": "Puncak Jaya", "display": "Puncak Jaya (Kabupaten)", "province": "Papua Tengah"},
  {"api": "Purbalingga", "display": "Purbalingga (Kabupaten)", "province": "Jawa Tengah"},
  {"api": "Purwakarta", "display": "Purwakarta (Kabupaten)", "province": "Jawa Barat"},
  {"api": "Purworejo", "display": "Purworejo (Kabupaten)", "province": "Jawa Tengah"},
  
  {"api": "Raja Ampat", "display": "Raja Ampat (Kabupaten)", "province": "Papua Barat Daya"},
  {"api": "Rejang Lebong", "display": "Rejang Lebong (Kabupaten)", "province": "Bengkulu"},
  {"api": "Rembang", "display": "Rembang (Kabupaten)", "province": "Jawa Tengah"},
  {"api": "Rokan Hilir", "display": "Rokan Hilir (Kabupaten)", "province": "Riau"},
  {"api": "Rokan Hulu", "display": "Rokan Hulu (Kabupaten)", "province": "Riau"},
  {"api": "Rote Ndao", "display": "Rote Ndao (Kabupaten)", "province": "Nusa Tenggara Timur"},
  
  {"api": "Sabang", "display": "Sabang (Kota)", "province": "Aceh"},
  {"api": "Sabu Raijua", "display": "Sabu Raijua (Kabupaten)", "province": "Nusa Tenggara Timur"},
  {"api": "Salatiga", "display": "Salatiga (Kota)", "province": "Jawa Tengah"},
  {"api": "Samarinda", "display": "Samarinda (Kota)", "province": "Kalimantan Timur"},
  {"api": "Sambas", "display": "Sambas (Kabupaten)", "province": "Kalimantan Barat"},
  {"api": "Samosir", "display": "Samosir (Kabupaten)", "province": "Sumatera Utara"},
  {"api": "Sampang", "display": "Sampang (Kabupaten)", "province": "Jawa Timur"},
  {"api": "Sanggau", "display": "Sanggau (Kabupaten)", "province": "Kalimantan Barat"},
  {"api": "Sarmi", "display": "Sarmi (Kabupaten)", "province": "Papua"},
  {"api": "Sarolangun", "display": "Sarolangun (Kabupaten)", "province": "Jambi"},
  {"api": "Sawahlunto", "display": "Sawahlunto (Kota)", "province": "Sumatera Barat"},
  {"api": "Sekadau", "display": "Sekadau (Kabupaten)", "province": "Kalimantan Barat"},
  {"api": "Seluma", "display": "Seluma (Kabupaten)", "province": "Bengkulu"},
  {"api": "Semarang", "display": "Semarang (Kota)", "province": "Jawa Tengah"},
  {"api": "Semarang", "display": "Semarang (Kabupaten)", "province": "Jawa Tengah"},
  {"api": "Seram Bagian Barat", "display": "Seram Bagian Barat (Kabupaten)", "province": "Maluku"},
  {"api": "Seram Bagian Timur", "display": "Seram Bagian Timur (Kabupaten)", "province": "Maluku"},
  {"api": "Serang", "display": "Serang (Kota)", "province": "Banten"},
  {"api": "Serang", "display": "Serang (Kabupaten)", "province": "Banten"},
  {"api": "Serdang Bedagai", "display": "Serdang Bedagai (Kabupaten)", "province": "Sumatera Utara"},
  {"api": "Seruyan", "display": "Seruyan (Kabupaten)", "province": "Kalimantan Tengah"},
  {"api": "Siak", "display": "Siak (Kabupaten)", "province": "Riau"},
  {"api": "Sibolga", "display": "Sibolga (Kota)", "province": "Sumatera Utara"},
  {"api": "Sidenreng Rappang", "display": "Sidenreng Rappang (Kabupaten)", "province": "Sulawesi Selatan"},
  {"api": "Sidoarjo", "display": "Sidoarjo (Kabupaten)", "province": "Jawa Timur"},
  {"api": "Sigi", "display": "Sigi (Kabupaten)", "province": "Sulawesi Tengah"},
  {"api": "Sijunjung", "display": "Sijunjung (Kabupaten)", "province": "Sumatera Barat"},
  {"api": "Sikka", "display": "Sikka (Kabupaten)", "province": "Nusa Tenggara Timur"},
  {"api": "Simalungun", "display": "Simalungun (Kabupaten)", "province": "Sumatera Utara"},
  {"api": "Simeulue", "display": "Simeulue (Kabupaten)", "province": "Aceh"},
  {"api": "Singkawang", "display": "Singkawang (Kota)", "province": "Kalimantan Barat"},
  {"api": "Sinjai", "display": "Sinjai (Kabupaten)", "province": "Sulawesi Selatan"},
  {"api": "Sintang", "display": "Sintang (Kabupaten)", "province": "Kalimantan Barat"},
  {"api": "Situbondo", "display": "Situbondo (Kabupaten)", "province": "Jawa Timur"},
  {"api": "Sleman", "display": "Sleman (Kabupaten)", "province": "DI Yogyakarta"},
  {"api": "Solok", "display": "Solok (Kota)", "province": "Sumatera Barat"},
  {"api": "Solok", "display": "Solok (Kabupaten)", "province": "Sumatera Barat"},
  {"api": "Solok Selatan", "display": "Solok Selatan (Kabupaten)", "province": "Sumatera Barat"},
  {"api": "Soppeng", "display": "Soppeng (Kabupaten)", "province": "Sulawesi Selatan"},
  {"api": "Sorong", "display": "Sorong (Kota)", "province": "Papua Barat Daya"},
  {"api": "Sorong", "display": "Sorong (Kabupaten)", "province": "Papua Barat"},
  {"api": "Sorong Selatan", "display": "Sorong Selatan (Kabupaten)", "province": "Papua Barat Daya"},
  {"api": "Sragen", "display": "Sragen (Kabupaten)", "province": "Jawa Tengah"},
  {"api": "Subang", "display": "Subang (Kabupaten)", "province": "Jawa Barat"},
  {"api": "Subulussalam", "display": "Subulussalam (Kota)", "province": "Aceh"},
  {"api": "Sukabumi", "display": "Sukabumi (Kota)", "province": "Jawa Barat"},
  {"api": "Sukabumi", "display": "Sukabumi (Kabupaten)", "province": "Jawa Barat"},
  {"api": "Sukamara", "display": "Sukamara (Kabupaten)", "province": "Kalimantan Tengah"},
  {"api": "Sukoharjo", "display": "Sukoharjo (Kabupaten)", "province": "Jawa Tengah"},
  {"api": "Sumba Barat", "display": "Sumba Barat (Kabupaten)", "province": "Nusa Tenggara Timur"},
  {"api": "Sumba Barat Daya", "display": "Sumba Barat Daya (Kabupaten)", "province": "Nusa Tenggara Timur"},
  {"api": "Sumba Tengah", "display": "Sumba Tengah (Kabupaten)", "province": "Nusa Tenggara Timur"},
  {"api": "Sumba Timur", "display": "Sumba Timur (Kabupaten)", "province": "Nusa Tenggara Timur"},
  {"api": "Sumbawa", "display": "Sumbawa (Kabupaten)", "province": "Nusa Tenggara Barat"},
  {"api": "Sumbawa Barat", "display": "Sumbawa Barat (Kabupaten)", "province": "Nusa Tenggara Barat"},
  {"api": "Sumedang", "display": "Sumedang (Kabupaten)", "province": "Jawa Barat"},
  {"api": "Sumenep", "display": "Sumenep (Kabupaten)", "province": "Jawa Timur"},
  {"api": "Sungai Penuh", "display": "Sungai Penuh (Kota)", "province": "Jambi"},
  {"api": "Supiori", "display": "Supiori (Kabupaten)", "province": "Papua"},
  {"api": "Surabaya", "display": "Surabaya (Kota)", "province": "Jawa Timur"},
  {"api": "Surakarta", "display": "Surakarta (Kota)", "province": "Jawa Tengah"},
  
  {"api": "Tabalong", "display": "Tabalong (Kabupaten)", "province": "Kalimantan Selatan"},
  {"api": "Tabanan", "display": "Tabanan (Kabupaten)", "province": "Bali"},
  {"api": "Takalar", "display": "Takalar (Kabupaten)", "province": "Sulawesi Selatan"},
  {"api": "Tambrauw", "display": "Tambrauw (Kabupaten)", "province": "Papua Barat"},
  {"api": "Tana Tidung", "display": "Tana Tidung (Kabupaten)", "province": "Kalimantan Utara"},
  {"api": "Tana Toraja", "display": "Tana Toraja (Kabupaten)", "province": "Sulawesi Selatan"},
  {"api": "Tanah Bumbu", "display": "Tanah Bumbu (Kabupaten)", "province": "Kalimantan Selatan"},
  {"api": "Tanah Datar", "display": "Tanah Datar (Kabupaten)", "province": "Sumatera Barat"},
  {"api": "Tanah Laut", "display": "Tanah Laut (Kabupaten)", "province": "Kalimantan Selatan"},
  {"api": "Tangerang", "display": "Tangerang (Kota)", "province": "Banten"},
  {"api": "Tangerang", "display": "Tangerang (Kabupaten)", "province": "Banten"},
  {"api": "Tangerang Selatan", "display": "Tangerang Selatan (Kota)", "province": "Banten"},
  {"api": "Tanggamus", "display": "Tanggamus (Kabupaten)", "province": "Lampung"},
  {"api": "Tanjung Balai", "display": "Tanjung Balai (Kota)", "province": "Sumatera Utara"},
  {"api": "Tanjung Jabung Barat", "display": "Tanjung Jabung Barat (Kabupaten)", "province": "Jambi"},
  {"api": "Tanjung Jabung Timur", "display": "Tanjung Jabung Timur (Kabupaten)", "province": "Jambi"},
  {"api": "Tanjung Pinang", "display": "Tanjung Pinang (Kota)", "province": "Kepulauan Riau"},
  {"api": "Tapanuli Selatan", "display": "Tapanuli Selatan (Kabupaten)", "province": "Sumatera Utara"},
  {"api": "Tapanuli Tengah", "display": "Tapanuli Tengah (Kabupaten)", "province": "Sumatera Utara"},
  {"api": "Tapanuli Utara", "display": "Tapanuli Utara (Kabupaten)", "province": "Sumatera Utara"},
  {"api": "Tapin", "display": "Tapin (Kabupaten)", "province": "Kalimantan Selatan"},
  {"api": "Tarakan", "display": "Tarakan (Kota)", "province": "Kalimantan Utara"},
  {"api": "Tasikmalaya", "display": "Tasikmalaya (Kota)", "province": "Jawa Barat"},
  {"api": "Tasikmalaya", "display": "Tasikmalaya (Kabupaten)", "province": "Jawa Barat"},
  {"api": "Tebing Tinggi", "display": "Tebing Tinggi (Kota)", "province": "Sumatera Utara"},
  {"api": "Tebo", "display": "Tebo (Kabupaten)", "province": "Jambi"},
  {"api": "Tegal", "display": "Tegal (Kota)", "province": "Jawa Tengah"},
  {"api": "Tegal", "display": "Tegal (Kabupaten)", "province": "Jawa Tengah"},
  {"api": "Teluk Bintuni", "display": "Teluk Bintuni (Kabupaten)", "province": "Papua Barat"},
  {"api": "Teluk Wondama", "display": "Teluk Wondama (Kabupaten)", "province": "Papua Barat"},
  {"api": "Temanggung", "display": "Temanggung (Kabupaten)", "province": "Jawa Tengah"},
  {"api": "Ternate", "display": "Ternate (Kota)", "province": "Maluku Utara"},
  {"api": "Tidore Kepulauan", "display": "Tidore Kepulauan (Kota)", "province": "Maluku Utara"},
  {"api": "Timor Tengah Selatan", "display": "Timor Tengah Selatan (Kabupaten)", "province": "Nusa Tenggara Timur"},
  {"api": "Timor Tengah Utara", "display": "Timor Tengah Utara (Kabupaten)", "province": "Nusa Tenggara Timur"},
  {"api": "Toba", "display": "Toba (Kabupaten)", "province": "Sumatera Utara"},
  {"api": "Tojo Una-Una", "display": "Tojo Una-Una (Kabupaten)", "province": "Sulawesi Tengah"},
  {"api": "Tolikara", "display": "Tolikara (Kabupaten)", "province": "Papua Pegunungan"},
  {"api": "Toli-Toli", "display": "Toli-Toli (Kabupaten)", "province": "Sulawesi Tengah"},
  {"api": "Tomohon", "display": "Tomohon (Kota)", "province": "Sulawesi Utara"},
  {"api": "Toraja Utara", "display": "Toraja Utara (Kabupaten)", "province": "Sulawesi Selatan"},
  {"api": "Trenggalek", "display": "Trenggalek (Kabupaten)", "province": "Jawa Timur"},
  {"api": "Tuban", "display": "Tuban (Kabupaten)", "province": "Jawa Timur"},
  {"api": "Tual", "display": "Tual (Kota)", "province": "Maluku"},
  {"api": "Tulang Bawang", "display": "Tulang Bawang (Kabupaten)", "province": "Lampung"},
  {"api": "Tulang Bawang Barat", "display": "Tulang Bawang Barat (Kabupaten)", "province": "Lampung"},
  {"api": "Tulungagung", "display": "Tulungagung (Kabupaten)", "province": "Jawa Timur"},
  
  {"api": "Wakatobi", "display": "Wakatobi (Kabupaten)", "province": "Sulawesi Tenggara"},
  {"api": "Wajo", "display": "Wajo (Kabupaten)", "province": "Sulawesi Selatan"},
  {"api": "Waropen", "display": "Waropen (Kabupaten)", "province": "Papua"},
  {"api": "Way Kanan", "display": "Way Kanan (Kabupaten)", "province": "Lampung"},
  {"api": "Wonogiri", "display": "Wonogiri (Kabupaten)", "province": "Jawa Tengah"},
  {"api": "Wonosobo", "display": "Wonosobo (Kabupaten)", "province": "Jawa Tengah"},
  
  {"api": "Yahukimo", "display": "Yahukimo (Kabupaten)", "province": "Papua Pegunungan"},
  {"api": "Yalimo", "display": "Yalimo (Kabupaten)", "province": "Papua Pegunungan"},
  {"api": "Yogyakarta", "display": "Yogyakarta (Kota)", "province": "DI Yogyakarta"}
]